pdfs/AnsiBib.py
pdfs/BaseWork.py
pdfs/Bases.py
pdfs/BibFormatter.py
pdfs/Bibtex.py
pdfs/Cache.py
pdfs/Crossref.py
pdfs/Database.py
pdfs/Exceptions.py
pdfs/ExtractDoi.py
pdfs/HTMLBib.py
pdfs/Main.py
pdfs/Prompt.py
pdfs/ReadPdf.py
pdfs/TermOutput.py
pdfs/TextSearch.py
pdfs/WorkTypes.py
pdfs/__init__.py
pdfs/unimap.py
pdfs/Commands/Add.py
pdfs/Commands/Attach.py
pdfs/Commands/Aux2Bib.py
pdfs/Commands/Bibtex.py
pdfs/Commands/Command.py
pdfs/Commands/Completers.py
pdfs/Commands/Edit.py
pdfs/Commands/Import.py
pdfs/Commands/Info.py
pdfs/Commands/Init.py
pdfs/Commands/List.py
pdfs/Commands/Search.py
pdfs/Commands/View.py
pdfs/Commands/WWW.py
pdfs/Commands/WatchDir.py
pdfs/Commands/__init__.py
pdfs/data/LTWA_20160915.txt
pdfs/static/favicon.ico
pdfs/static/style.css
pdfs/templates/bibliography.html
pdfs-0.1.0.dist-info/DESCRIPTION.rst
pdfs-0.1.0.dist-info/METADATA
pdfs-0.1.0.dist-info/RECORD
pdfs-0.1.0.dist-info/WHEEL
pdfs-0.1.0.dist-info/entry_points.txt
pdfs-0.1.0.dist-info/metadata.json
pdfs-0.1.0.dist-info/top_level.txt
