Metadata-Version: 1.2
Name: pdfs
Version: 0.1.0
Summary: Simple bibliography manager
Home-page: https://github.com/tmearnest/pdfs
Author: Tyler M. Earnest
Author-email: tylere@rne.st
License: MIT License
Keywords: doi,bibtex,pdf,bibliography
Platform: UNKNOWN
Classifier: Intended Audience :: Developers
Classifier: Intended Audience :: Education
Classifier: Intended Audience :: Science/Research
Classifier: License :: OSI Approved :: MIT License
Classifier: Natural Language :: English
Classifier: Operating System :: POSIX :: Linux
Classifier: Development Status :: 3 - Alpha
Requires-Python: >=3.6
